lamp_runtime/__init__.py
lamp_runtime/lamp_runtime.py
lamp_runtime/extensions/__init__.py
lamp_runtime/extensions/computer_use.py
lamp_runtime-0.1.0.dist-info/licenses/LICENSE
lamp_runtime-0.1.0.dist-info/METADATA
lamp_runtime-0.1.0.dist-info/WHEEL
lamp_runtime-0.1.0.dist-info/top_level.txt
lamp_runtime-0.1.0.dist-info/RECORD
