Metadata-Version: 2.4
Name: lamp-runtime
Version: 0.1.0
Summary: A client library to interact with the Lamp Runtime Sandbox on Kubernetes.
Project-URL: Homepage, https://github.com/mlamp/LampRuntime
Project-URL: Bug Tracker, https://github.com/mlamp/LampRuntime/issues
Classifier: Programming Language :: Python :: 3
Classifier: License :: OSI Approved :: Apache Software License
Classifier: Operating System :: OS Independent
Requires-Python: >=3.7
License-File: LICENSE
Requires-Dist: kubernetes
Requires-Dist: requests
Provides-Extra: test
Requires-Dist: pytest; extra == "test"
Requires-Dist: pytest-xdist; extra == "test"
Dynamic: license-file
